{
  "title": "Sen to Chihiro no Kamikakushi",
  "altTitle": "Spirited Away",
  "cover": "https://cdn.myanimelist.net/images/anime/6/79597.jpg",
  "genre": ["Adventure", "Supernatural", "Fantasy"],
  "description": "Chihiro, gadis kecil yang terperangkap di dunia roh, harus bekerja di pemandian milik penyihir Yubaba untuk menyelamatkan orang tuanya yang berubah menjadi babi dan menemukan jalan pulang.",
  "video": "vidio.html#spirited-away",
  "production": "Studio Ghibli",
  "release": "Juli 2001",
  "rating": "8.8",
  "episodes": [
    {
      "number": 1,
      "url": ""
    }
  ]
}
