{
  "title": "Watari-kun no xx ga Houkai Sunzen",
  "altTitle": "Watari-kun's ****** Is about to Collapse",
  "cover": "https://cdn.myanimelist.net/images/anime/1502/150545l.jpg",
  "genre": ["Romance", "Drama", "Comedy"],
  "description": "Setelah kehilangan keluarganya, Watari Naoto hidup dengan adik perempuannya dan mencoba menjalani kehidupan sekolah yang tenang. Namun, kemunculan kembali seseorang dari masa lalunya membuat dunianya perlahan runtuh. 1",
  "video": "vidio.html#watari-kun-no-xx-ga-houkai-sunzen",
  "production": "Passione",
  "release": "4 Oktober 2025",
  "rating": "",
  "episodes": [
    {
      "number": 1,
      "url": ""
    }
  ]
}
